ziper/__init__.py
ziper/iter.py
ziper/py.typed
ziper-0.1.5.dist-info/LICENSE
ziper-0.1.5.dist-info/METADATA
ziper-0.1.5.dist-info/WHEEL
ziper-0.1.5.dist-info/RECORD
