Metadata-Version: 2.1
Name: ziper
Version: 0.1.5
Summary: Rust-like iterator for Python
Home-page: https://github.com/cospectrum/ziper
License: Apache-2.0
Author: cospectrum
Author-email: severinalexeyv@gmail.com
Requires-Python: >=3.7,<4.0
Classifier: License :: OSI Approved :: Apache Software License
Classifier: Programming Language :: Python :: 3
Classifier: Programming Language :: Python :: 3.7
Classifier: Programming Language :: Python :: 3.8
Classifier: Programming Language :: Python :: 3.9
Classifier: Programming Language :: Python :: 3.10
Classifier: Programming Language :: Python :: 3.11
Requires-Dist: more-itertools (>=9.1.0,<10.0.0)
Project-URL: Repository, https://github.com/cospectrum/ziper
